.hgignore
.installed.cfg
.project
.pydevproject
LICENSE
MANIFEST.in
README.txt
bootstrap.py
buildout.cfg
setup.py
bin/buildout
docs/HISTORY.txt
docs/README.txt
src/ztfy/__init__.py
src/ztfy.utils.egg-info/PKG-INFO
src/ztfy.utils.egg-info/SOURCES.txt
src/ztfy.utils.egg-info/dependency_links.txt
src/ztfy.utils.egg-info/entry_points.txt
src/ztfy.utils.egg-info/namespace_packages.txt
src/ztfy.utils.egg-info/not-zip-safe
src/ztfy.utils.egg-info/requires.txt
src/ztfy.utils.egg-info/top_level.txt
src/ztfy/utils/__init__.py
src/ztfy/utils/component.py
src/ztfy/utils/configure.zcml
src/ztfy/utils/container.py
src/ztfy/utils/date.py
src/ztfy/utils/decorator.py
src/ztfy/utils/encoding.py
src/ztfy/utils/file.py
src/ztfy/utils/html.py
src/ztfy/utils/interfaces.py
src/ztfy/utils/list.py
src/ztfy/utils/overrides.zcml
src/ztfy/utils/profilehooks.py
src/ztfy/utils/property.py
src/ztfy/utils/request.py
src/ztfy/utils/schema.py
src/ztfy/utils/security.py
src/ztfy/utils/session.py
src/ztfy/utils/site.py
src/ztfy/utils/size.py
src/ztfy/utils/text.py
src/ztfy/utils/traversing.py
src/ztfy/utils/unicode.py
src/ztfy/utils/zodb.py
src/ztfy/utils/zodb.zcml
src/ztfy/utils/browser/__init__.py
src/ztfy/utils/browser/configure.zcml
src/ztfy/utils/browser/encoding.py
src/ztfy/utils/browser/zodb.py
src/ztfy/utils/catalog/__init__.py
src/ztfy/utils/catalog/configure.zcml
src/ztfy/utils/catalog/index.py
src/ztfy/utils/doctests/README.txt
src/ztfy/utils/locales/ztfy.utils.pot
src/ztfy/utils/locales/en/LC_MESSAGES/ztfy.utils.mo
src/ztfy/utils/locales/en/LC_MESSAGES/ztfy.utils.po
src/ztfy/utils/locales/fr/LC_MESSAGES/ztfy.utils.mo
src/ztfy/utils/locales/fr/LC_MESSAGES/ztfy.utils.po
src/ztfy/utils/protocol/__init__.py
src/ztfy/utils/protocol/http.py
src/ztfy/utils/protocol/xmlrpc.py
src/ztfy/utils/tal/__init__.py
src/ztfy/utils/tal/configure.zcml
src/ztfy/utils/tal/fanstatic.py
src/ztfy/utils/tal/html.py
src/ztfy/utils/tal/interfaces.py
src/ztfy/utils/tal/request.py
src/ztfy/utils/tal/session.py
src/ztfy/utils/tal/text.py
src/ztfy/utils/tests/__init__.py
src/ztfy/utils/tests/test_utilsdocs.py
src/ztfy/utils/tests/test_utilsdocstrings.py
src/ztfy/utils/timezone/__init__.py
src/ztfy/utils/timezone/configure.zcml
src/ztfy/utils/timezone/interfaces.py
src/ztfy/utils/timezone/schema.py
